README.md
setup.py
peutils/__init__.py
peutils/common_util.py
peutils/comutil.py
peutils/datautil.py
peutils/fileutil.py
peutils/image_util.py
peutils/mailutil.py
peutils/matrix_util.py
peutils/ossutil.py
peutils/pcd_py3.py
peutils/pcd_util.py
peutils/storage_util.py
peutils/test_collect.py
peutils/textutil.py
peutils/toolutil.py
peutils/transutil.py
peutils/url_util.py
peutils/wooeyutil.py
peutils.egg-info/PKG-INFO
peutils.egg-info/SOURCES.txt
peutils.egg-info/dependency_links.txt
peutils.egg-info/top_level.txt
peutils/a9_process/__init__.py
peutils/a9_process/v1.py
peutils/pc_tools/__init__.py
peutils/pc_tools/registration/__init__.py
peutils/pc_tools/registration/ipc_registration.py
peutils/process/__init__.py
peutils/process/v1.py
peutils/transform/__init__.py
peutils/transform/v1/__init__.py
peutils/transform/v1/base.py
peutils/transform/v1/case_test.py
peutils/transform/v1/audio_seg/__init__.py
peutils/transform/v1/audio_seg/parser.py
peutils/transform/v1/audio_seg/pre_parser.py
peutils/transform/v1/img_com/__init__.py
peutils/transform/v1/img_com/parser.py
peutils/transform/v1/img_com/pre_parser.py
peutils/transform/v1/lidar_box/__init__.py
peutils/transform/v1/lidar_box/parser.py
peutils/transform/v1/lidar_box/pre_parser.py
peutils/transform/v1/lidar_manifest/__init__.py
peutils/transform/v1/lidar_manifest/parser.py
peutils/transform/v1/lidar_point/__init__.py
peutils/transform/v1/lidar_point/parser.py
peutils/transform/v1/report/__init__.py
peutils/transform/v1/report/executor.py
peutils/transform/v1/task/__init__.py
peutils/transform/v1/task/executor.py
peutils/transform/v1/tools/__init__.py
peutils/transform/v1/tools/lidar.py
peutils/transform/v1/tools/lidar_cal_point.py
peutils/transform/v1/tools/lidar_point.py
peutils/transform/v2/__init__.py
peutils/transform/v2/base.py
peutils/transform/v2/lidar_box/__init__.py
peutils/transform/v2/lidar_box/parser.py
peutils/transform/v2/lidar_box/pre_parser.py
peutils/transform/v2/lidar_manifest/__init__.py
peutils/transform/v2/lidar_manifest/parser.py
peutils/transform/v2/task/__init__.py
peutils/transform/v2/task/executor.py